Workbook

Sheet Assumptions
A1: SmartAppt — DB Sizing Assumptions (edit BLUE cells)
A2: Parameter | B2: Value | C2: Unit | D2: Notes
A3: Number of associations (tenants) | B3: 500 | C3: associations | D3: Active paying associations
A4: Units per association (avg) | B4: 80 | C4: units | D4: Apartments / flats per society
A5: Users per unit (avg) | B5: 2 | C5: users | D5: Registered residents + co-owners
A6: Staff per association (avg) | B6: 5 | C6: users | D6: Manager, treasurer, gate staff, committee
A7: Gate entries / unit / day | B7: 2 | C7: entries/day | D7: Visitor log entries per occupied unit
A8: Maintenance tickets / unit / year | B8: 8 | C8: tickets/yr | D8: Service requests raised by residents
A9: Bill cycles per year | B9: 12 | C9: cycles/yr | D9: Monthly billing is typical
A10: One-time dues / unit / year | B10: 3 | C10: dues/yr | D10: Penalties, special charges
A11: Payments per bill | B11: 1.1 | C11: payments | D11: Partial/late payments slightly > 1
A12: Announcements / assoc / month | B12: 4 | C12: ann/mo | D12: Notices, circulars
A13: Documents / assoc / year | B13: 20 | C13: docs/yr | D13: AGM minutes, rules, certs
A14: Expenses / assoc / month | B14: 15 | C14: expenses/mo | D14: Vendor bills, maintenance, utilities
... A18: Months of data to size for | B18: 36 | C18: months | D18: 3 years default
A19: Derived Totals (auto-calculated)
A20: Total active users | B20: =B3*B5+B3*B6 -> 3500 | C20: users | D20: assoc × users_pu + assoc × staff_pa
A21: Total units | B21: =B3*B4 -> 40000 | C21: units | D21: assoc × units_pa
A22: Total occupied units | B22: =B3*B4*0.9 -> 36000 | C22: units | D22: 90% occupancy assumption
A23: Days in sizing window | B23: =B18*30 -> 1080 | C23: days | D23: months × 30

Sheet Table Sizing
A1: SmartAppt — PostgreSQL Table-Level Sizing
A2: Table | B2: Category | C2: Row Size (bytes) | D2: Row Count Formula | E2: Estimated Rows | F2: Data Size (MB) | G2: Index Multiplier | H2: Total Size (MB)
A3: Association | B3: Core | C3: 512 | D3: =Assumptions!$B$3 -> 500 | E3: =D3 -> 500 | F3: =E3*C3/1048576 -> 0.24414062 | G3: 1.2 | H3: =F3*G3 -> 0.29296875
A4: AssociationConfig | B4: Core | C4: 256 | D4: =Assumptions!$B$3 -> 500 | E4: =D4 -> 500 | F4: =E4*C4/1048576 -> 0.12207031 | G4: 1.1 | H4: =F4*G4 -> 0.13427734
A5: Unit | B5: Core | C5: 256 | D5: =Assumptions!$B$3*Assumptions!$B$4 -> 40000 | E5: =D5 -> 40000 | F5: =E5*C5/1048576 -> 9.765625 | G5: 1.2 | H5: =F5*G5 -> 11.71875
A6: User | B6: Core | C6: 384 | D6: =Assumptions!$B$3*(Assumptions!$B$4*Assumptions!$B$5+Assumptions!$B$6) -> 82500 | E6: =D6 -> 82500 | F6: =E6*C6/1048576 -> 30.212402 | G6: 1.3 | H6: =F6*G6 -> 39.276123
A7: UserInvite | B7: Core | C7: 128 | D7: =Assumptions!$B$3*Assumptions!$B$4*0.3 -> 12000 | E7: =D7 -> 12000 | F7: =E7*C7/1048576 -> 1.4648438 | G7: 1.1 | H7: =F7*G7 -> 1.6113281
A8: RefreshToken | B8: Core | C8: 128 | D8: =Assumptions!$B$3*(Assumptions!$B$4*Assumptions!$B$5+Assumptions!$B$6)*3 -> 247500 | E8: =D8 -> 247500 | F8: =E8*C8/1048576 -> 30.212402 | G8: 1.1 | H8: =F8*G8 -> 33.233643
A9: MaintenanceTicket | B9: Maintenance | C9: 512 | D9: =Assumptions!$B$3*Assumptions!$B$4*0.9*Assumptions!$B$8*(Assumptions!$B$18/12) -> 864000 | E9: =D9 -> 864000 | F9: =E9*C9/1048576 -> 421.875 | G9: 1.4 | H9: =F9*G9 -> 590.625
A10: TicketAttachment | B10: Maintenance | C10: 256 | D10: =Assumptions!$B$3*Assumptions!$B$4*0.9*Assumptions!$B$8*(Assumptions!$B$18/12)*1.5 -> 1296000 | E10: =D10 -> 1296000 | F10: =E10*C10/1048576 -> 316.40625 | G10: 1.2 | H10: =F10*G10 -> 379.6875
A11: TicketStatusLog | B11: Maintenance | C11: 192 | D11: =Assumptions!$B$3*Assumptions!$B$4*0.9*Assumptions!$B$8*(Assumptions!$B$18/12)*3 -> 2592000 | E11: =D11 -> 2592000 | F11: =E11*C11/1048576 -> 474.60938 | G11: 1.2 | H11: =F11*G11 -> 569.53125
A12: DuesConfig | B12: Financial | C12: 192 | D12: =Assumptions!$B$3*2 -> 1000 | E12: =D12 -> 1000 | F12: =E12*C12/1048576 -> 0.18310547 | G12: 1.1 | H12: =F12*G12 -> 0.20141602
A13: Bill | B13: Financial | C13: 320 | D13: =Assumptions!$B$3*Assumptions!$B$4*Assumptions!$B$9*(Assumptions!$B$18/12) -> 1440000 | E13: =D13 -> 1440000 | F13: =E13*C13/1048576 -> 439.45312 | G13: 1.3 | H13: =F13*G13 -> 571.28906
A14: OneTimeDue | B14: Financial | C14: 256 | D14: =Assumptions!$B$3*Assumptions!$B$4*0.9*Assumptions!$B$10*(Assumptions!$B$18/12) -> 324000 | E14: =D14 -> 324000 | F14: =E14*C14/1048576 -> 79.101562 | G14: 1.2 | H14: =F14*G14 -> 94.921875
A15: Payment | B15: Financial | C15: 256 | D15: =Assumptions!$B$3*Assumptions!$B$4*Assumptions!$B$9*(Assumptions!$B$18/12)*Assumptions!$B$11 -> 1584000 | E15: =D15 -> 1584000 | F15: =E15*C15/1048576 -> 386.71875 | G15: 1.3 | H15: =F15*G15 -> 502.73438
A16: OtherReceipt | B16: Financial | C16: 256 | D16: =Assumptions!$B$3*Assumptions!$B$4*0.5*(Assumptions!$B$18/12) -> 60000 | E16: =D16 -> 60000 | F16: =E16*C16/1048576 -> 14.648438 | G16: 1.2 | H16: =F16*G16 -> 17.578125
A17: Vendor | B17: Financial | C17: 256 | D17: =Assumptions!$B$3*20 -> 10000 | E17: =D17 -> 10000 | F17: =E17*C17/1048576 -> 2.4414062 | G17: 1.2 | H17: =F17*G17 -> 2.9296875
A18: Expense | B18: Financial | C18: 384 | D18: =Assumptions!$B$3*Assumptions!$B$14*Assumptions!$B$18 -> 270000 | E18: =D18 -> 270000 | F18: =E18*C18/1048576 -> 98.876953 | G18: 1.3 | H18: =F18*G18 -> 128.54004
A19: ExpenseBudget | B19: Financial | C19: 192 | D19: =Assumptions!$B$3*12*(Assumptions!$B$18/12) -> 18000 | E19: =D19 -> 18000 | F19: =E19*C19/1048576 -> 3.2958984 | G19: 1.2 | H19: =F19*G19 -> 3.9550781
A20: ExpenseCategoryConfig | B20: Financial | C20: 128 | D20: =Assumptions!$B$3*15 -> 7500 | E20: =D20 -> 7500 | F20: =E20*C20/1048576 -> 0.91552734 | G20: 1.1 | H20: =F20*G20 -> 1.0070801
A21: RecurringExpense | B21: Financial | C21: 256 | D21: =Assumptions!$B$3*5 -> 2500 | E21: =D21 -> 2500 | F21: =E21*C21/1048576 -> 0.61035156 | G21: 1.1 | H21: =F21*G21 -> 0.67138672
A22: Account | B22: Accounting | C22: 192 | D22: =Assumptions!$B$3*50 -> 25000 | E22: =D22 -> 25000 | F22: =E22*C22/1048576 -> 4.5776367 | G22: 1.2 | H22: =F22*G22 -> 5.4931641
A23: JournalEntry | B23: Accounting | C23: 256 | D23: =Assumptions!$B$3*Assumptions!$B$14*Assumptions!$B$18 -> 270000 | E23: =D23 -> 270000 | F23: =E23*C23/1048576 -> 65.917969 | G23: 1.2 | H23: =F23*G23 -> 79.101562
A24: JournalLine | B24: Accounting | C24: 192 | D24: =Assumptions!$B$3*Assumptions!$B$14*Assumptions!$B$18*Assumptions!$B$15 -> 540000 | E24: =D24 -> 540000 | F24: =E24*C24/1048576 -> 98.876953 | G24: 1.3 | H24: =F24*G24 -> 128.54004
A25: Announcement | B25: Communication | C25: 384 | D25: =Assumptions!$B$3*Assumptions!$B$12*Assumptions!$B$18 -> 72000 | E25: =D25 -> 72000 | F25: =E25*C25/1048576 -> 26.367188 | G25: 1.2 | H25: =F25*G25 -> 31.640625
A26: AnnouncementRead | B26: Communication | C26: 128 | D26: =Assumptions!$B$3*Assumptions!$B$12*Assumptions!$B$18*Assumptions!$B$4*0.6 -> 3456000 | E26: =D26 -> 3456000 | F26: =E26*C26/1048576 -> 421.875 | G26: 1.2 | H26: =F26*G26 -> 506.25
A27: Document | B27: Communication | C27: 256 | D27: =Assumptions!$B$3*Assumptions!$B$13*(Assumptions!$B$18/12) -> 30000 | E27: =D27 -> 30000 | F27: =E27*C27/1048576 -> 7.3242188 | G27: 1.1 | H27: =F27*G27 -> 8.0566406
A28: Poll | B28: Communication | C28: 256 | D28: =Assumptions!$B$3*Assumptions!$B$16*(Assumptions!$B$18/12) -> 9000 | E28: =D28 -> 9000 | F28: =E28*C28/1048576 -> 2.1972656 | G28: 1.2 | H28: =F28*G28 -> 2.6367188
A29: PollVote | B29: Communication | C29: 128 | D29: =Assumptions!$B$3*Assumptions!$B$16*(Assumptions!$B$18/12)*Assumptions!$B$4*0.5 -> 360000 | E29: =D29 -> 360000 | F29: =E29*C29/1048576 -> 43.945312 | G29: 1.2 | H29: =F29*G29 -> 52.734375
A30: Visitor | B30: Gate | C30: 384 | D30: =Assumptions!$B$3*Assumptions!$B$4*0.9*Assumptions!$B$7*Assumptions!$B$23 -> 77760000 | E30: =D30 -> 77760000 | F30: =E30*C30/1048576 -> 28476.562 | G30: 1.3 | H30: =F30*G30 -> 37019.531
A31: FrequentVisitor | B31: Gate | C31: 192 | D31: =Assumptions!$B$3*Assumptions!$B$4*5 -> 200000 | E31: =D31 -> 200000 | F31: =E31*C31/1048576 -> 36.621094 | G31: 1.2 | H31: =F31*G31 -> 43.945312
A32: AuditLog | B32: Audit | C32: 384 | D32: =Assumptions!$B$3*(Assumptions!$B$4*Assumptions!$B$5+Assumptions!$B$6)*Assumptions!$B$17*Assumptions!$B$23 -> 445500000 | E32: =D32 -> 445500000 | F32: =E32*C32/1048576 -> 163146.97 | G32: 1.2 | H32: =F32*G32 -> 195776.37
A33: MenuGroupConfig | B33: Config | C33: 96 | D33: =Assumptions!$B$3*10 -> 5000 | E33: =D33 -> 5000 | F33: =E33*C33/1048576 -> 0.45776367 | G33: 1.1 | H33: =F33*G33 -> 0.50354004
A34: MobileConfig | B34: Config | C34: 96 | D34: =Assumptions!$B$3 -> 500 | E34: =D34 -> 500 | F34: =E34*C34/1048576 -> 0.045776367 | G34: 1.1 | H34: =F34*G34 -> 0.050354004
A35: TOTAL | E35: =SUM(E3:E34) -> 537079500 | F35: =SUM(F3:F34) -> 194642.9 | H35: =SUM(H3:H34) -> 236604.79

Sheet Projections
A1: SmartAppt — Multi-Year DB Growth Projections
A2: Parameter | B2: Value | C2: Notes
A3: Annual tenant growth rate | B3: 0.4 | C3: 40% YoY — typical SaaS growth phase
A4: Annual data-per-tenant growth | B4: 0.1 | C4: Existing tenants accumulate more data
A5: Overhead / TOAST / WAL factor | B5: 0.3 | C5: PostgreSQL bloat, WAL, system tables
A6: Year-by-Year DB Size (all tables combined)
A7: Year | B7: Associations | C7: Base DB (MB) | D7: Scaled DB (MB) | E7: Overhead (MB) | F7: Total DB (GB)
A8: Year 1 | B8: =Assumptions!$B$3*(1+$B$3)^(1-1) -> 500 | C8: ='Table Sizing'!$H$35 -> 236604.79 | D8: =C8 -> 236604.79 | E8: =D8*$B$5 -> 70981.437 | F8: =(D8+E8)/1024 -> 300.37717
A9: Year 2 | B9: =Assumptions!$B$3*(1+$B$3)^(2-1) -> 700 | C9: ='Table Sizing'!$H$35*(1+$B$3)^(2-1)*(1+$B$4)^(2-1) -> 364371.38 | D9: =C9 -> 364371.38 | E9: =D9*$B$5 -> 109311.41 | F9: =(D9+E9)/1024 -> 462.58085
A10: Year 3 | B10: =Assumptions!$B$3*(1+$B$3)^(3-1) -> 980 | C10: ='Table Sizing'!$H$35*(1+$B$3)^(3-1)*(1+$B$4)^(3-1) -> 561131.92 | D10: =C10 -> 561131.92 | E10: =D10*$B$5 -> 168339.58 | F10: =(D10+E10)/1024 -> 712.37451
A11: Year 4 | B11: =Assumptions!$B$3*(1+$B$3)^(4-1) -> 1372 | C11: ='Table Sizing'!$H$35*(1+$B$3)^(4-1)*(1+$B$4)^(4-1) -> 864143.16 | D11: =C11 -> 864143.16 | E11: =D11*$B$5 -> 259242.95 | F11: =(D11+E11)/1024 -> 1097.0567
A12: Year 5 | B12: =Assumptions!$B$3*(1+$B$3)^(5-1) -> 1920.8 | C12: ='Table Sizing'!$H$35*(1+$B$3)^(5-1)*(1+$B$4)^(5-1) -> 1330780.5 | D12: =C12 -> 1330780.5 | E12: =D12*$B$5 -> 399234.14 | F12: =(D12+E12)/1024 -> 1689.4674
A14: Note: Add 2× for WAL archiving + replicas in HA/standby setups. Sizes are logical-row estimates before compression.

Sheet S3 Storage
A1: SmartAppt — Object / S3 Storage Sizing (separate from PostgreSQL)
A2: Asset Type | B2: Source Table | C2: Avg File Size (KB) | D2: Items (all tenants, sizing window) | E2: Annual Storage (GB) | F2: 3-Year Storage (GB) | G2: Notes
A3: Ticket attachments | B3: TicketAttachment | C3: 500 | D3: =Assumptions!$B$3*Assumptions!$B$4*0.9*Assumptions!$B$8*(Assumptions!$B$18/12)*1.5 -> 1296000 | E3: =D3*C3/1048576 -> 617.98096 | F3: =E3*3*1.3 -> 2410.1257 | G3: Photos, PDFs with maintenance requests
A4: Society documents | B4: Document | C4: 1200 | D4: =Assumptions!$B$3*Assumptions!$B$13*(Assumptions!$B$18/12) -> 30000 | E4: =D4*C4/1048576 -> 34.332275 | F4: =E4*3*1.3 -> 133.89587 | G4: AGM minutes, rules, NOC letters
A5: Payment receipts | B5: Payment | C5: 80 | D5: =Assumptions!$B$3*Assumptions!$B$4*Assumptions!$B$9*(Assumptions!$B$18/12)*Assumptions!$B$11 -> 1584000 | E5: =D5*C5/1048576 -> 120.84961 | F5: =E5*3*1.3 -> 471.31348 | G5: Auto-generated PDF receipts
A6: Profile photos | B6: User | C6: 120 | D6: =Assumptions!$B$3*(Assumptions!$B$4*Assumptions!$B$5+Assumptions!$B$6)*0.5 -> 41250 | E6: =D6*C6/1048576 -> 4.7206879 | F6: =E6*3*1.3 -> 18.410683 | G6: ~50% of users upload
A7: Association logos | B7: Association | C7: 50 | D7: =Assumptions!$B$3 -> 500 | E7: =D7*C7/1048576 -> 0.023841858 | F7: =E7*3*1.3 -> 0.092983246 | G7: One per tenant
A8: Expense invoices | B8: Expense | C8: 400 | D8: =Assumptions!$B$3*Assumptions!$B$14*Assumptions!$B$18*0.7 -> 189000 | E8: =D8*C8/1048576 -> 72.097778 | F8: =E8*3*1.3 -> 281.18134 | G8: Vendor invoices attached to expenses
A9: Visitor ID photos | B9: Visitor | C9: 200 | D9: =Assumptions!$B$3*Assumptions!$B$4*0.9*Assumptions!$B$7*Assumptions!$B$23*0.3 -> 23328000 | E9: =D9*C9/1048576 -> 4449.4629 | F9: =E9*3*1.3 -> 17352.905 | G9: 30% of visitors have face/ID capture
A10: TOTAL | E10: =SUM(E3:E9) -> 5299.468 | F10: =SUM(F3:F9) -> 20667.925

Sheet Summary
A1: SmartAppt — Sizing Summary & Infrastructure Recommendations
A2: DATABASE (PostgreSQL)
A3: Year 1 total DB size (GB) | B3: =Projections!F8 -> 300.37717
A4: Year 3 total DB size (GB) | B4: =Projections!F10 -> 712.37451
A5: Year 5 total DB size (GB) | B5: =Projections!F12 -> 1689.4674
A6: Tables sized | B6: 32
A7: Largest table (by volume) | B7: AuditLog (visitor + audit logging)
A8: OBJECT STORAGE (S3 / compatible)
A9: Year 1 S3 storage (GB) | B9: ='S3 Storage'!E10 -> 5299.468
A10: 3-year S3 storage (GB) | B10: ='S3 Storage'!F10 -> 20667.925
A11: INFRASTRUCTURE RECOMMENDATIONS
A12: Year 1 — Instance | B12: db.t4g.large (2 vCPU, 8 GB RAM, ~50 GB gp3)
A13: Year 3 — Instance | B13: db.m7g.xlarge (4 vCPU, 16 GB RAM, ~200 GB gp3)
A14: Year 5 — Instance | B14: db.m7g.2xlarge (8 vCPU, 32 GB RAM) or Aurora Serverless v2
A15: Storage type | B15: gp3 SSD with autoscaling (start 100 GB)
A16: Backup retention | B16: 7-day PITR + weekly snapshots to S3
A17: Connection pooling | B17: PgBouncer / RDS Proxy — mandatory at >200 associations
A18: Partitioning | B18: Partition AuditLog & Visitor by month; archive >12 months
A19: Multi-tenant isolation | B19: Row-level via association_id; add RLS policies for defence-in-depth
A20: Index strategy | B20: GIN index on JSON cols; partial indexes on association_id+status
A21: ESTIMATED MONTHLY COST (AWS RDS, us-east-1)
A22: Year 1 / month (USD) | B22: 150
A23: Year 3 / month (USD) | B23: 480
A24: Year 5 / month (USD) | B24: 950
A25: Cost source | B25: AWS RDS PostgreSQL on-demand pricing, us-east-1, Jul 2026 — update via aws.amazon.com/rds/postgresql/pricing/
